{
    "customer_id": "MSG-25816265164681487",
    "profile": {
        "first_name": "ทิพย์",
        "last_name": "กิจสุนทร",
        "nick_name": "ทิพย์",
        "status": "Active",
        "membership_tier": "GENERAL",
        "lifecycle_stage": "In Progress",
        "agent": "พรพล ธนสุวรรณธาร",
        "join_date": "2026-02-09T05:30:18+0000"
    },
    "contact_info": {
        "facebook": "ทิพย์ กิจสุนทร",
        "facebook_id": "25816265164681487",
        "lead_channel": "Facebook"
    },
    "intelligence": {
        "metrics": {
            "total_spend": 0,
            "total_learning_hours": 0,
            "total_point": 0,
            "total_order": 0
        },
        "tags": [
            "Facebook Chat",
            "Contacted"
        ]
    },
    "inventory": {
        "coupons": [],
        "learning_courses": []
    },
    "wallet": {
        "balance": 0,
        "points": 0,
        "currency": "THB"
    },
    "timeline": [
        {
            "id": "SYNC-1770904425507-75",
            "date": "2026-02-09T05:30:18+0000",
            "type": "SYSTEM",
            "summary": "Synced from Facebook Messenger",
            "details": {
                "content": "Customer imported from Facebook Page conversation."
            }
        }
    ]
}